easygui_tk/__init__.py
easygui_tk/core.py
easygui_tk-1.0.0.dist-info/licenses/LICENSE
easygui_tk-1.0.0.dist-info/METADATA
easygui_tk-1.0.0.dist-info/WHEEL
easygui_tk-1.0.0.dist-info/top_level.txt
easygui_tk-1.0.0.dist-info/RECORD
