Metadata-Version: 2.4
Name: easygui-tk
Version: 1.0.0
Summary: A modern, declarative Tkinter wrapper.
Home-page: https://github.com/ikeman32/EasyGui_TK_Project
Author: David Isakson
Author-email: david.isakson.ii@gmail.com
Classifier: License :: OSI Approved :: MIT License
Classifier: Programming Language :: Python :: 3
Classifier: Operating System :: OS Independent
Requires-Python: >=3.7
License-File: LICENSE
Dynamic: author
Dynamic: author-email
Dynamic: classifier
Dynamic: description
Dynamic: description-content-type
Dynamic: home-page
Dynamic: license-file
Dynamic: requires-python
Dynamic: summary
